{
	"Version": 3,
	"Meta": {
		"Duration": 2,
		"Fps": 30.0,
		"Loop": true,
		"AreBeziersRestricted": false,
		"CurveCount": 4,
		"TotalSegmentCount": 14,
		"TotalPointCount": 42,
		"UserDataCount": 0,
		"TotalUserDataSize": 0
	},
	"Curves": [
		{
			"Target": "Parameter",
			"Id": "milk_move",
			"Segments": [
				0,
				-30,
				0,
				0.9,
				30,
				0,
				2,
				30
			]
		},
		{
			"Target": "Parameter",
			"Id": "tatuCHIKACHIKA",
			"Segments": [
				0,
				-30,
				1,
				0.167,
				-30,
				0.333,
				30,
				0.5,
				30,
				1,
				0.667,
				30,
				0.833,
				-30,
				1,
				-30,
				1,
				1.167,
				-30,
				1.333,
				30,
				1.5,
				30,
				1,
				1.667,
				30,
				1.833,
				-30,
				2,
				-30
			]
		},
		{
			"Target": "Parameter",
			"Id": "ParamMouthOpenY",
			"Segments": [
				0,
				0.4,
				1,
				0.167,
				0.4,
				0.333,
				0.7,
				0.5,
				0.7,
				1,
				0.667,
				0.7,
				0.833,
				0.4,
				1,
				0.4,
				1,
				1.167,
				0.4,
				1.333,
				0.7,
				1.5,
				0.7,
				1,
				1.667,
				0.7,
				1.833,
				0.4,
				2,
				0.4
			]
		},
		{
			"Target": "Parameter",
			"Id": "ParamBreath",
			"Segments": [
				0,
				0,
				1,
				0.167,
				0,
				0.333,
				0.4,
				0.5,
				0.4,
				1,
				0.667,
				0.4,
				0.833,
				0,
				1,
				0,
				1,
				1.156,
				0,
				1.311,
				0.5,
				1.467,
				0.5,
				1,
				1.644,
				0.5,
				1.822,
				0,
				2,
				0
			]
		}
	]
}